test_atml/__init__.py
test_atml/timmins/__init__.py
test_atml-0.0.15.dist-info/METADATA
test_atml-0.0.15.dist-info/WHEEL
test_atml-0.0.15.dist-info/entry_points.txt
test_atml-0.0.15.dist-info/top_level.txt
test_atml-0.0.15.dist-info/RECORD
