Metadata-Version: 2.2
Name: test_atml
Version: 0.0.15
Summary: The test projetc.
Classifier: Programming Language :: Python :: 3
Classifier: License :: OSI Approved :: MIT License
Classifier: Operating System :: OS Independent
Requires-Python: >=3.10
Requires-Dist: requests
Provides-Extra: aio
Requires-Dist: aiohttp; extra == "aio"
Provides-Extra: redis
Requires-Dist: redis; extra == "redis"
Dynamic: requires-dist
